Workbook

Sheet Investimento
B7: PLANEJADOR DE INDEPENDÊNCIA FINANCEIRA COM FIIs
B8: Descubra quando você poderá viver de renda
B10: Preencha apenas os campos com borda azul.
B12: SEUS DADOS FINANCEIROS
B13: Quanto você já tem investido em FIIs? | E13: 10000
B14: Quanto você pode investir por mês? | E14: 500
B15: Qual renda mensal você precisa para viver? | E15: 5000
B16: Rendimento médio mensal esperado | E16: 0.006
B18: SUA META DE INDEPENDÊNCIA
B19: Patrimônio necessário para viver de renda | E19: =$E$15/$E$16 -> 833333.33
B20: Falta acumular ainda | E20: =$E$19-$E$13 -> 823333.33
B21: Tempo estimado para atingir meta | E21: =INT(NPER(E16,-E14,-E13,E19)/12)&" anos e "&ROUND(MOD(NPER(E16,-E14,-E13,E19,),12),0)&" meses " -> 31 anos e 10 meses
B22: Renda mensal | E22: =E19*E16 -> 5000
B24: PATRIMÔNIO
B25: Em anos | C25: Total Acumulado | E25: Dividendos
B26: 4 | C26: =FV(E16,$B$26*12,-E14) -> 27717.502 | E26: =$C$26*E16 -> 166.30501
B28: ESTRATÉGIAS DE INVESTIMENTO
B29: Veja quanto acumularia com cada estratégia
B30: Escolha seu perfil | E30: Agressivo
B32: Rendimento Mensal | E32: Aporte Mensal
B33: =VLOOKUP(E30,'Inputs - Apoio'!A2:C4,2,0) -> 0.01 | E33: =VLOOKUP(E30,'Inputs - Apoio'!A2:C4,3,0) -> 500
B35: QUANTO VOCÊ TERÁ ACUMULADO
A36: 5 | B36: Patrimônio em 5 anos | E36: =FV(B33,5*12,-E33,E13,0) -> 22667.868
A37: 10 | B37: Patrimônio em 10 anos | E37: =FV(B33,10*12,-E33,$E$13,0) -> 82015.476
A38: 15 | B38: Patrimônio em 15 anos | E38: =FV(B33,15*12,-E33,$E$13,0) -> 189832.08
A39: 20 | B39: Patrimônio em 20 anos | E39: =FV(B33,20*12,-E33,$E$13,0) -> 385702.15
B41: DIVERSIFICAÇÃO DA CARTEIRA
B42: Ideias de como distribuir seu investimento mensal de acordo com seu perfil
C44: Perfil | E44: Agressivo
C45: Valor a investir por mês | E45: 1000
B47: Tipos de FII | D47: Percentual Sugerido | E47: Valor
B48: Papel | D48: =VLOOKUP($E$44&"-"&B48,'Inputs - Apoio'!$A$6:$D$24,4,0) -> 0.5 | E48: =$D$48*$E$45 -> 500
B49: Tijolo | D49: =VLOOKUP($E$44&"-"&B49,'Inputs - Apoio'!$A$6:$D$24,4,0) -> 0.1 | E49: =$D$49*$E$45 -> 100
B50: HÍbridos | D50: =VLOOKUP($E$44&"-"&B50,'Inputs - Apoio'!$A$6:$D$24,4,0) -> 0.05 | E50: =$D$50*$E$45 -> 50
B51: Fofs | D51: =VLOOKUP($E$44&"-"&B51,'Inputs - Apoio'!$A$6:$D$24,4,0) -> 0.05 | E51: =$D$51*$E$45 -> 50
B52: Desenvolvimento | D52: =VLOOKUP($E$44&"-"&B52,'Inputs - Apoio'!$A$6:$D$24,4,0) -> 0.2 | E52: =$D$52*$E$45 -> 200
B53: Hotelarias | D53: =VLOOKUP($E$44&"-"&B53,'Inputs - Apoio'!$A$6:$D$24,4,0) -> 0.1 | E53: =$D$53*$E$45 -> 100

Sheet Inputs - Apoio
A1: Perfil | B1: Rendimento mensal (%) | C1: Aporte Mensal (R$)
A2: Conservador | B2: 0.006 | C2: =Investimento!$E$14 -> 500
A3: Moderado | B3: 0.008 | C3: =Investimento!$E$14 -> 500
A4: Agressivo | B4: 0.01 | C4: =Investimento!$E$14 -> 500
A6: Chave | B6: Perfil | C6: Tipo de FII | D6: % | G6: %
A7: =B7&"-"&C7 -> Conservador-PAPEL | B7: Conservador | C7: PAPEL | D7: 0.3 | F7: Moderado-TIJOLO | G7: =VLOOKUP(F7,$A:$D,4,FALSE) -> 0.35
A8: =B8&"-"&C8 -> Conservador-TIJOLO | B8: Conservador | C8: TIJOLO | D8: 0.5
A9: =B9&"-"&C9 -> Conservador-HÍBRIDOS | B9: Conservador | C9: HÍBRIDOS | D9: 0.1
A10: =B10&"-"&C10 -> Conservador-FOFs | B10: Conservador | C10: FOFs | D10: 0.1
A11: =B11&"-"&C11 -> Conservador-DESENVOLVIMENTO | B11: Conservador | C11: DESENVOLVIMENTO | D11: 0
A12: =B12&"-"&C12 -> Conservador-HOTELARIAS | B12: Conservador | C12: HOTELARIAS | D12: 0
A13: =B13&"-"&C13 -> Moderado-PAPEL | B13: Moderado | C13: PAPEL | D13: 0.32
A14: =B14&"-"&C14 -> Moderado-TIJOLO | B14: Moderado | C14: TIJOLO | D14: 0.35
A15: =B15&"-"&C15 -> Moderado-HÍBRIDOS | B15: Moderado | C15: HÍBRIDOS | D15: 0.08
A16: =B16&"-"&C16 -> Moderado-FOFs | B16: Moderado | C16: FOFs | D16: 0.05
A17: =B17&"-"&C17 -> Moderado-DESENVOLVIMENTO | B17: Moderado | C17: DESENVOLVIMENTO | D17: 0.1
A18: =B18&"-"&C18 -> Moderado-HOTELARIAS | B18: Moderado | C18: HOTELARIAS | D18: 0.1
A19: =B19&"-"&C19 -> Agressivo-PAPEL | B19: Agressivo | C19: PAPEL | D19: 0.5
... A24: =B24&"-"&C24 -> Agressivo-HOTELARIAS | B24: Agressivo | C24: HOTELARIAS | D24: 0.1
